dev_tools/__init__.py
dev_tools/custom_decorators.py
dev_tools/custom_handlers.py
dev_tools/debug_tools.py
dev_tools/logger_settings.py
dev_tools/progress_bar.py
tests/__init__.py
tests/test_custom_decorators.py
tests/test_custom_handlers.py
tests/test_debug_tools.py
tests/test_logger_settings.py
tests/test_progress_bar.py
bosos_dev_tools-0.1.4.dist-info/LICENSE
bosos_dev_tools-0.1.4.dist-info/METADATA
bosos_dev_tools-0.1.4.dist-info/WHEEL
bosos_dev_tools-0.1.4.dist-info/top_level.txt
bosos_dev_tools-0.1.4.dist-info/RECORD
