Metadata-Version: 2.1
Name: bosos-dev-tools
Version: 0.1.4
Summary: Dev Tools is a collection of utility tools for Python developers, designed to simplify debugging, logging, and monitoring tasks. This package includes custom logging handlers, decorators for measuring execution time, and a progress bar utility to enhance the development workflow.
Author-email: Björn Gunnarsson <bosos3@hotmail.com>
License: MIT License
Project-URL: Source, https://github.com/bjorngun/developer-tools
Project-URL: Tracker, https://github.com/bjorngun/developer-tools/issues
Keywords: development,tools,logging,decorators
Classifier: Development Status :: 4 - Beta
Classifier: Programming Language :: Python :: 3
Classifier: Programming Language :: Python :: 3.10
Classifier: Programming Language :: Python :: 3.11
Classifier: Programming Language :: Python :: 3.12
Classifier: Intended Audience :: Developers
Classifier: Topic :: Software Development :: Build Tools
Classifier: License :: OSI Approved :: MIT License
Classifier: Operating System :: OS Independent
Requires-Python: >=3.10
License-File: LICENSE
Requires-Dist: pyodbc
Requires-Dist: python-dotenv
Provides-Extra: lint
Requires-Dist: pylint; extra == "lint"
Provides-Extra: test
Requires-Dist: coverage; extra == "test"
